{
   "harvest_menu" : {
      "name" : "Récolter",
      "description" : "Récolter les ressources du sol comme du bois, de la pierre et des minerais.",
      "class" : "dock",
      "icon" : "/stonehearth/ui/game/start_menu/images/dock_harvest.png",
      "hotkey" : "1",
      "game_mode" : "normal",
      "clickSound": "stonehearth:sounds:ui:start_menu:harvest_pickup"
   },
   "build_menu" : {
      "name" : "Construction & Modèle",
      "description" : "Construire des structures comme les maisons et les murs de la ville.",
      "class" : "dock",
      "icon" : "/stonehearth/ui/game/start_menu/images/dock_build.png",
      "hotkey" : "2",
      "game_mode" : "build",
      "menuHideSound": "stonehearth:sounds:ui:start_menu:wash_out",
      "menuShowSound": "stonehearth:sounds:ui:start_menu:wash_in",
      "items" : {
      "building_templates" : {
            "name" : "Construire un bâtiment",
            "description" : "Construction de bâtiments comme les maisons et tours",
            "class" : "button",
            "icon" : "/stonehearth/ui/game/start_menu/images/design_building.png",
            "sticky" : true,
            "hotkey" : "b"
         },
         "place_item" : {
            "name" : "Placer un l'objet",
            "description" : "Placer les articles comme les meubles et la décoration",
            "class" : "button",
            "icon" : "/stonehearth/ui/game/start_menu/images/place_item.png",
            "sticky" : true,
            "hotkey" : "p"
         },
         "build_road" : {
            "name" : "Construire une Route",
            "description" : "Ajouter des routes à votre ville",
            "class" : "button",
            "icon" : "/stonehearth/ui/game/start_menu/images/roads.png",
            "sticky" : true,
            "hotkey" : ""
         },
         "build_ladder" : {
            "name" : "Construire une échelle",
            "description" : "Construire une échelle pour atteindre des endroits difficile d'accès",
            "class" : "button",
            "icon" : "/stonehearth/ui/game/start_menu/images/build_ladder.png",
            "sticky" : true,
            "hotkey" : "l"
         }
      }
   },
   "mining_menu" : {
      "name" : "Mine & Paysage",
      "description" : "Changer la forme du terrain, avec les mines et l'aménagement paysager",
      "class" : "dock",
      "icon" : "/stonehearth/ui/game/start_menu/images/dock_mine.png",
      "hotkey" : "3",
      "game_mode" : "mining",
      "clickSound": "stonehearth:sounds:ui:start_menu:trigger_click",
      "items" : {
         "mining_ui" : {
            "name" : "Mine",
            "description" : "Mine des tunnels et des grottes",
            "class" : "button",
            "icon" : "/stonehearth/ui/game/start_menu/images/mine.png",
            "sticky" : true,
            "hotkey" : "m"
         }
      }
   },   
   "fight_menu" : {
      "name" : "Combattre & Défendre",
      "description" : "Gérer vos forces de combat",
      "class" : "dock",
      "hotkey" : "6",
      "icon" : "/stonehearth/ui/game/start_menu/images/dock_defend.png",
      "game_mode" : "normal",
      "menuHideSound": "stonehearth:sounds:ui:start_menu:defend_close",
      "menuShowSound": "stonehearth:sounds:ui:start_menu:defend_open",
      "items" : {
         "red_alert" : {
            "name" : "Alerte Rouge!",
            "description" : "Rassemble les travailleurs pour défendre la ville!",
            "class" : "button",
            "icon" : "/stonehearth/ui/game/start_menu/images/red_alert.png",
            "sticky" : true,
            "hotkey" : "r"
         }
      }
   },   
   "town_menu" : {
      "name" : "Infos sur la ville",
      "description" : "Informations générales sur votre ville, comment vos citoyens se sentent, et la richesse que vous avez accumulé!",
      "class" : "dock",
      "icon" : "/stonehearth/ui/game/start_menu/images/town_banner.png",
      "hotkey" : "i",
      "game_mode" : "normal",
      "clickSound": "stonehearth:sounds:banner_grab"
   },   
   "zone_menu" : {
      "name" : "Désigner des Zones",
      "description" : "Désigner des zones au sol pour le stockage, l'agriculture, etc.",
      "class" : "dock",
      "icon" : "/stonehearth/ui/game/start_menu/images/dock_zone.png",
      "hotkey" : "4",
      "game_mode" : "zones",
      "menuHideSound": "stonehearth:sounds:ui:start_menu:wash_out",
      "menuShowSound": "stonehearth:sounds:ui:start_menu:wash_in",
      "items" : {
         "create_stockpile" : {
            "name" : "Réserve",
            "description" : "Placer une réserve pour stocker des ressources.",
            "class" : "button",
            "icon" : "/stonehearth/ui/game/start_menu/images/zone_stockpile.png",
            "sticky" : true,
            "hotkey" : "o"
         },
         "create_farm" : {
            "name" : "Champs",
            "description" : "Placer un champ sur le sol.",
            "class" : "button",
            "icon" : "/stonehearth/ui/game/start_menu/images/zone_farm.png",
            "sticky" : true,
            "hotkey" : "f"
         },
         "create_trapping_grounds" : {
            "name" : "Zone de Piège",
            "description" : "Placer des pièges pour capturer de petites bestioles.",
            "class" : "button",
            "icon" : "/stonehearth/ui/game/start_menu/images/zone_trap.png",
            "sticky" : true,
            "hotkey" : "t"
         }, 
         "create_pasture" : {
            "name" : "Pâturage animal",
            "description" : "Le berger apportera des animaux ici pour qu'il broute.",
            "class" : "button",
            "icon" : "/stonehearth/ui/game/start_menu/images/zone_pasture.png",
            "sticky" : true
         }
      }
   },
   "citizen_manager" : {
      "name" : "Gérer les citoyens",
      "description" : "Gérer vos colons et les promouvoir auprès des nouveaux emplois.",
      "class" : "dock",
      "icon" : "/stonehearth/ui/game/start_menu/images/citizens.png",
      "hotkey" : "5",
      "game_mode" : "normal",
      "menuHideSound": "stonehearth:sounds:ui:start_menu:jobs_close",
      "menuShowSound": "stonehearth:sounds:ui:start_menu:jobs_open"
   },
   "dead_button" : {
      "name" : "TBD",
      "description" : "Nous avons un emplacement à utiliser. Une Idées ?",
      "class" : "dock",
      "icon" : "/stonehearth/ui/game/start_menu/images/dead.png",
      "hotkey" : "7",
      "game_mode" : "normal",
      "menuHideSound": "stonehearth:sounds:ui:start_menu:jobs_close",
      "menuShowSound": "stonehearth:sounds:ui:start_menu:jobs_open"
   },
   "tasks_manager" : {
      "name" : "Gestion des tâches",
      "description" : "Tâche à effectuer.",
      "class" : "dock",
      "icon" : "/stonehearth/ui/game/start_menu/images/tasks.png",
      "hotkey" : "7",
      "game_mode" : "normal",
      "menuHideSound": "stonehearth:sounds:ui:start_menu:jobs_close",
      "menuShowSound": "stonehearth:sounds:ui:start_menu:jobs_open"
   }   
}
